Metadata-Version: 2.4
Name: openwfs
Version: 1.1.0
Summary: A library for performing wavefront shaping experiments and simulations
Author: Jeroen Doornbos, Daniël Cox, Arnon A. B., Swapnil Mache
Author-email: Ivo Vellekoop <i.m.vellekoop@utwente.nl>
License-Expression: BSD-3-Clause
Project-URL: Homepage, https://github.com/ivovellekoop/openwfs
Project-URL: Documentation, https://openwfs.readthedocs.io/en/latest/
Project-URL: Repository, https://github.com/ivovellekoop/openwfs
Project-URL: Issues, https://github.com/ivovellekoop/openwfs/issues
Keywords: wavefront,optics,simulation,microscopy,hardware
Classifier: Programming Language :: Python :: 3
Classifier: Development Status :: 4 - Beta
Classifier: Operating System :: OS Independent
Requires-Python: <4.0,>=3.10
License-File: LICENCE.txt
Requires-Dist: numpy>=1.25.2
Requires-Dist: astropy>=6.0.0
Requires-Dist: opencv-python>=4.9.0.80
Requires-Dist: matplotlib>=3.7.3
Requires-Dist: scipy>=1.11.3
Requires-Dist: annotated-types>=0.7.0
Provides-Extra: nidaq
Requires-Dist: nidaqmx>=1.0.1; extra == "nidaq"
Provides-Extra: genicam
Requires-Dist: harvesters>=1.4.2; python_version < "3.12" and extra == "genicam"
Provides-Extra: opengl
Requires-Dist: PyOpenGL>=3.1.7; extra == "opengl"
Requires-Dist: glfw>=2.5.9; extra == "opengl"
Provides-Extra: zaber
Requires-Dist: zaber-motion>=4.0.0; extra == "zaber"
Requires-Dist: pyserial>=3.5; extra == "zaber"
Provides-Extra: all
Requires-Dist: nidaqmx>=1.0.1; extra == "all"
Requires-Dist: harvesters>=1.4.2; python_version < "3.12" and extra == "all"
Requires-Dist: PyOpenGL>=3.1.7; extra == "all"
Requires-Dist: glfw>=2.5.9; extra == "all"
Requires-Dist: zaber-motion>=4.0.0; extra == "all"
Requires-Dist: pyserial>=3.5; extra == "all"
Provides-Extra: dev
Requires-Dist: scikit-image>=0.21.0; extra == "dev"
Requires-Dist: pytest>=7.0.0; extra == "dev"
Requires-Dist: nidaqmx>=1.0.1; extra == "dev"
Requires-Dist: black>=25.1.0; extra == "dev"
Requires-Dist: poetry>=1.2.0; extra == "dev"
Provides-Extra: docs
Requires-Dist: sphinx>=4.1.2; extra == "docs"
Requires-Dist: sphinx_mdinclude>=0.5.0; extra == "docs"
Requires-Dist: sphinx-rtd-theme>=2.0.0; extra == "docs"
Requires-Dist: sphinx-autodoc-typehints>=2.2.0; extra == "docs"
Requires-Dist: sphinxcontrib-bibtex>=2.6.0; extra == "docs"
Requires-Dist: sphinx-markdown-builder==0.6.7; extra == "docs"
Requires-Dist: sphinx-gallery>=0.15.0; extra == "docs"
Dynamic: license-file
